<?xml version="1.0" encoding="UTF-8"?>
<!DOCTYPE properties SYSTEM "http://java.sun.com/dtd/properties.dtd">
<properties>
    <!-- Configuration properties in database (ORACLE) -->
    <entry key="environment.metamac.configuration.db.url">jdbc:oracle:thin:@preistac.gobiernodecanarias.net:1576:PREISTAC</entry>
    <entry key="environment.metamac.configuration.db.username">istac_commons_metadata</entry>
    <entry key="environment.metamac.configuration.db.password">e9XA3Rf4LIo8GnGpIKGb1hYdTT9/YVge</entry>
    <entry key="environment.metamac.configuration.db.driver_name">oracle.jdbc.OracleDriver</entry>
    <!-- Additional configuration -->
    <entry key="environment.metamac.portal.installation_type">INTERNAL</entry> <!-- Posibles valores: INTERNAL / EXTERNAL -->

</properties>
